commonlib_reader/__init__.py
commonlib_reader/connector.py
commonlib_reader/facility.py
commonlib_reader/ims.py
commonlib_reader/tag.py
commonlib_reader/unit.py
commonlib_reader/utils.py
commonlib_reader-1.0.8.dist-info/METADATA
commonlib_reader-1.0.8.dist-info/WHEEL
commonlib_reader-1.0.8.dist-info/RECORD
