Metadata-Version: 2.3
Name: commonlib-reader
Version: 1.0.8
Summary: Reader for Equinor commonlib api.
License: MIT
Author: Åsmund Våge Fannemel
Author-email: asmf@equinor.com
Requires-Python: >=3.10,<4.0.0
Classifier: License :: OSI Approved :: MIT License
Classifier: Programming Language :: Python :: 3
Classifier: Programming Language :: Python :: 3.10
Classifier: Programming Language :: Python :: 3.11
Classifier: Programming Language :: Python :: 3.12
Classifier: Programming Language :: Python :: 3.13
Requires-Dist: eq-api-connector (>=1.0.0,<2.0.0)
Requires-Dist: pandas (>=2.1.4)
Requires-Dist: requests (>=2.32.4)
Requires-Dist: urllib3 (>=2.5.0)
Project-URL: Repository, https://github.com/equinor/commonlib-reader.git
